{
  "flow": {
    "date": "2026-03-09",
    "industry": {
      "电子信息": 113.36,
      "发电设备": 41.32,
      "电器行业": 31.8,
      "煤炭行业": 25.77,
      "电力行业": 22.4,
      "造纸行业": 11.15,
      "仪器仪表": 8.23,
      "印刷包装": 8.16,
      "塑料制品": 6.3,
      "农药化肥": 4.4,
      "食品行业": 3.55,
      "纺织行业": 2.41,
      "化纤行业": 2.06,
      "石油行业": 1.92,
      "摩托车": 0.87,
      "传媒娱乐": 0.69,
      "化工行业": 0.5,
      "家具行业": 0.07,
      "玻璃行业": -0.48,
      "纺织机械": -0.61,
      "供水供气": -0.72,
      "公路桥梁": -1.15,
      "医疗器械": -1.2,
      "陶瓷行业": -1.39,
      "酿酒行业": -1.49,
      "酒店旅游": -1.51,
      "电子器件": -1.52,
      "汽车制造": -1.55,
      "环保行业": -1.73,
      "开发区": -1.73
    },
    "concept": {
      "光伏": 127.84,
      "光伏概念": 84.44,
      "重组概念": 68.48,
      "风电": 57.26,
      "网络游戏": 50.65,
      "锂矿": 43.18,
      "充电桩": 43.07,
      "物联网": 40.04,
      "盐湖提锂": 39.78,
      "特斯拉": 37.22,
      "锂电池": 33.72,
      "业绩预升": 33.11,
      "碳中和": 32.42,
      "鸿蒙概念": 31.82,
      "博彩概念": 31.49,
      "华为鸿蒙": 30.03,
      "股权激励": 29.0,
      "文化振兴": 28.05,
      "低碳经济": 25.09,
      "风能": 24.76,
      "涉矿概念": 24.65,
      "智能电网": 23.31,
      "TOPCon": 22.96,
      "钠电池": 21.97,
      "核电核能": 20.88,
      "含B股": 19.85,
      "恒大概念": 19.35,
      "HIT电池": 18.73,
      "HJT电池": 18.73,
      "皖江区域": 18.42
    }
  },
  "sentiment": {
    "hot_stocks": [
      {
        "name": "拓维信息",
        "code": "002261",
        "rank": 1
      },
      {
        "name": "华胜天成",
        "code": "600410",
        "rank": 2
      },
      {
        "name": "美利云",
        "code": "000815",
        "rank": 3
      },
      {
        "name": "金开新能",
        "code": "600821",
        "rank": 4
      },
      {
        "name": "宁德时代",
        "code": "300750",
        "rank": 5
      },
      {
        "name": "协鑫集成",
        "code": "002506",
        "rank": 6
      },
      {
        "name": "中国长城",
        "code": "000066",
        "rank": 7
      },
      {
        "name": "顺钠股份",
        "code": "000533",
        "rank": 8
      },
      {
        "name": "协鑫能科",
        "code": "002015",
        "rank": 9
      },
      {
        "name": "洲际油气",
        "code": "600759",
        "rank": 10
      },
      {
        "name": "中国西电",
        "code": "601179",
        "rank": 11
      },
      {
        "name": "豫能控股",
        "code": "001896",
        "rank": 12
      },
      {
        "name": "宁波建工",
        "code": "601789",
        "rank": 13
      },
      {
        "name": "汉缆股份",
        "code": "002498",
        "rank": 14
      },
      {
        "name": "南网能源",
        "code": "003035",
        "rank": 15
      },
      {
        "name": "云赛智联",
        "code": "600602",
        "rank": 16
      },
      {
        "name": "大位科技",
        "code": "600589",
        "rank": 17
      },
      {
        "name": "中国能建",
        "code": "601868",
        "rank": 18
      },
      {
        "name": "华工科技",
        "code": "000988",
        "rank": 19
      },
      {
        "name": "优刻得",
        "code": "688158",
        "rank": 20
      },
      {
        "name": "网宿科技",
        "code": "300017",
        "rank": 21
      },
      {
        "name": "同花顺",
        "code": "300033",
        "rank": 22
      },
      {
        "name": "航天发展",
        "code": "000547",
        "rank": 23
      },
      {
        "name": "比亚迪",
        "code": "002594",
        "rank": 24
      },
      {
        "name": "国电南自",
        "code": "600268",
        "rank": 25
      },
      {
        "name": "太阳电缆",
        "code": "002300",
        "rank": 26
      },
      {
        "name": "鸿博股份",
        "code": "002229",
        "rank": 27
      },
      {
        "name": "顺网科技",
        "code": "300113",
        "rank": 28
      },
      {
        "name": "三变科技",
        "code": "002112",
        "rank": 29
      },
      {
        "name": "中国石油",
        "code": "601857",
        "rank": 30
      }
    ]
  }
}